CheckYourSum/__init__.py
CheckYourSum/check_your_sum.py
Check_Your_Sum-1.0.1.dist-info/LICENSE
Check_Your_Sum-1.0.1.dist-info/METADATA
Check_Your_Sum-1.0.1.dist-info/WHEEL
Check_Your_Sum-1.0.1.dist-info/top_level.txt
Check_Your_Sum-1.0.1.dist-info/RECORD
